rfpipe/__init__.py
rfpipe/calibration.py
rfpipe/candidates.py
rfpipe/fileLock.py
rfpipe/flagging.py
rfpipe/metadata.py
rfpipe/pipeline.py
rfpipe/preferences.py
rfpipe/reproduce.py
rfpipe/search.py
rfpipe/source.py
rfpipe/state.py
rfpipe/util.py
rfpipe/version.py
rfpipe-1.3.7.dist-info/LICENSE
rfpipe-1.3.7.dist-info/METADATA
rfpipe-1.3.7.dist-info/WHEEL
rfpipe-1.3.7.dist-info/top_level.txt
rfpipe-1.3.7.dist-info/RECORD
